Metadata-Version: 2.1
Name: statsmodels
Version: 0.14.3
Summary: Statistical computations and models for Python
Home-page: https://www.statsmodels.org/
Download-URL: 
Maintainer: statsmodels Developers
Maintainer-email: pystatsmodels@googlegroups.com
License: BSD License
Project-URL: Bug Tracker, https://github.com/statsmodels/statsmodels/issues
Project-URL: Documentation, https://www.statsmodels.org/stable/index.html
Project-URL: Source Code, https://github.com/statsmodels/statsmodels
Platform: any
Classifier: Development Status :: 4 - Beta
Classifier: Environment :: Console
Classifier: Programming Language :: Cython
Classifier: Programming Language :: Python :: 3.9
Classifier: Programming Language :: Python :: 3.10
Classifier: Programming Language :: Python :: 3.11
Classifier: Programming Language :: Python :: 3.12
Classifier: Operating System :: OS Independent
Classifier: Intended Audience :: End Users/Desktop
Classifier: Intended Audience :: Developers
Classifier: Intended Audience :: Science/Research
Classifier: Natural Language :: English
Classifier: License :: OSI Approved :: BSD License
Classifier: Topic :: Office/Business :: Financial
Classifier: Topic :: Scientific/Engineering
Requires-Python: >=3.9
License-File: LICENSE.txt
Requires-Dist: numpy<3,>=1.22.3
Requires-Dist: scipy!=1.9.2,>=1.8
Requires-Dist: pandas!=2.1.0,>=1.4
Requires-Dist: patsy>=0.5.6
Requires-Dist: packaging>=21.3
Provides-Extra: build
Requires-Dist: cython>=3.0.10; extra == "build"
Provides-Extra: develop
Requires-Dist: cython>=3.0.10; extra == "develop"
Requires-Dist: cython<4,>=3.0.10; extra == "develop"
Requires-Dist: setuptools_scm[toml]~=8.0; extra == "develop"
Requires-Dist: matplotlib>=3; extra == "develop"
Requires-Dist: colorama; extra == "develop"
Requires-Dist: joblib; extra == "develop"
Requires-Dist: pytest<8,>=7.3.0; extra == "develop"
Requires-Dist: pytest-randomly; extra == "develop"
Requires-Dist: pytest-xdist; extra == "develop"
Requires-Dist: pytest-cov; extra == "develop"
Requires-Dist: pywinpty; os_name == "nt" and extra == "develop"
Requires-Dist: flake8; extra == "develop"
Requires-Dist: isort; extra == "develop"
Provides-Extra: docs
Requires-Dist: sphinx; extra == "docs"
Requires-Dist: nbconvert; extra == "docs"
Requires-Dist: jupyter_client; extra == "docs"
Requires-Dist: ipykernel; extra == "docs"
Requires-Dist: matplotlib; extra == "docs"
Requires-Dist: nbformat; extra == "docs"
Requires-Dist: numpydoc; extra == "docs"
Requires-Dist: pandas-datareader; extra == "docs"
